ing_ynab-3.0.1.dist-info/METADATA
ing_ynab-3.0.1.dist-info/WHEEL
ing_ynab-3.0.1.dist-info/licenses/LICENSE
ing_ynab/__init__.py
ing_ynab/__main__.py
ing_ynab/cli.py
ing_ynab/ing.py
ing_ynab/ynab.py
ing_ynab-3.0.1.dist-info/RECORD
