Metadata-Version: 2.1
Name: ing-ynab
Version: 3.0.1
Summary: Import your ING Germany bank statements via FinTS into YNAB.
Author-Email: Arne Bahlo <hey@arne.me>
License: MIT
Requires-Python: >=3.7
Requires-Dist: requests
Requires-Dist: fints>=4.0.0
Requires-Dist: enum-tools>=0.12.0
